aws_rotate/__init__.py
aws_rotate-0.0.3.dist-info/METADATA
aws_rotate-0.0.3.dist-info/RECORD
aws_rotate-0.0.3.dist-info/WHEEL
aws_rotate-0.0.3.dist-info/entry_points.txt
aws_rotate-0.0.3.dist-info/top_level.txt
